README.md
setup.py
zscaler_pulumi_zpa/__init__.py
zscaler_pulumi_zpa/_inputs.py
zscaler_pulumi_zpa/_utilities.py
zscaler_pulumi_zpa/app_connector_assistant_schedule.py
zscaler_pulumi_zpa/application_segment.py
zscaler_pulumi_zpa/application_segment_browser_access.py
zscaler_pulumi_zpa/application_segment_inspection.py
zscaler_pulumi_zpa/application_segment_multimatch_bulk.py
zscaler_pulumi_zpa/application_segment_pra.py
zscaler_pulumi_zpa/application_segment_weightedlb_config.py
zscaler_pulumi_zpa/application_server.py
zscaler_pulumi_zpa/browser_access.py
zscaler_pulumi_zpa/browser_certificate.py
zscaler_pulumi_zpa/c2_cip_ranges.py
zscaler_pulumi_zpa/cloud_browser_isolation_banner.py
zscaler_pulumi_zpa/cloud_browser_isolation_certificate.py
zscaler_pulumi_zpa/cloud_browser_isolation_external_profile.py
zscaler_pulumi_zpa/connector_group.py
zscaler_pulumi_zpa/emergency_access_user.py
zscaler_pulumi_zpa/get_app_connector_assistant_schedule.py
zscaler_pulumi_zpa/get_app_connector_controller.py
zscaler_pulumi_zpa/get_app_connector_group.py
zscaler_pulumi_zpa/get_application_segment.py
zscaler_pulumi_zpa/get_application_segment_browser_access.py
zscaler_pulumi_zpa/get_application_segment_by_type.py
zscaler_pulumi_zpa/get_application_segment_inspection.py
zscaler_pulumi_zpa/get_application_segment_multimatch_bulk.py
zscaler_pulumi_zpa/get_application_segment_pra.py
zscaler_pulumi_zpa/get_application_segment_weightedlb_config.py
zscaler_pulumi_zpa/get_application_server.py
zscaler_pulumi_zpa/get_ba_certificate.py
zscaler_pulumi_zpa/get_branch_connector_group.py
zscaler_pulumi_zpa/get_browser_protection.py
zscaler_pulumi_zpa/get_c2_cip_ranges.py
zscaler_pulumi_zpa/get_cloud_browser_isolation_banner.py
zscaler_pulumi_zpa/get_cloud_browser_isolation_certificate.py
zscaler_pulumi_zpa/get_cloud_browser_isolation_external_profile.py
zscaler_pulumi_zpa/get_cloud_browser_isolation_region.py
zscaler_pulumi_zpa/get_cloud_browser_isolation_zpa_profile.py
zscaler_pulumi_zpa.egg-info/PKG-INFO
zscaler_pulumi_zpa.egg-info/SOURCES.txt
zscaler_pulumi_zpa.egg-info/dependency_links.txt
zscaler_pulumi_zpa.egg-info/not-zip-safe
zscaler_pulumi_zpa.egg-info/requires.txt
zscaler_pulumi_zpa.egg-info/top_level.txt
