Metadata-Version: 2.4
Name: zscaler_pulumi_zpa
Version: 1.0.3
Summary: A Pulumi package for creating and managing Zscaler Private Access (ZPA) cloud resources.
Home-page: https://www.zscaler.com
License: MIT
Project-URL: Repository, https://github.com/zscaler/pulumi-zpa
Keywords: pulumi zpa zscaler category/cloud
Requires-Python: >=3.9
Requires-Dist: parver>=0.2.1
Requires-Dist: pulumi<4.0.0,>=3.0.0
Requires-Dist: semver>=2.8.1
Requires-Dist: typing-extensions<5,>=4.11; python_version < "3.11"
Dynamic: description
Dynamic: description-content-type
Dynamic: home-page
Dynamic: keywords
Dynamic: license
Dynamic: project-url
Dynamic: requires-dist
Dynamic: requires-python
Dynamic: summary
